my_package/client.py
my_package/server.py
pythonSftpServerManuel-0.0.2.dist-info/LICENSE
pythonSftpServerManuel-0.0.2.dist-info/METADATA
pythonSftpServerManuel-0.0.2.dist-info/WHEEL
pythonSftpServerManuel-0.0.2.dist-info/top_level.txt
pythonSftpServerManuel-0.0.2.dist-info/RECORD
